<?xml version='1.0' encoding='utf-8'?>
<Document xmlns="urn:iso:std:iso:20022:tech:xsd:camt.054.001.10"><BkToCstmrDbtCdtNtfctn><GrpHdr><MsgId>MSG21278180-GJGVHP</MsgId><CreDtTm>2024-04-24T01:01:11+03:00</CreDtTm></GrpHdr><Ntfctn><Id>1466872</Id><CreDtTm>2024-04-24T01:01:11+03:00</CreDtTm><Acct><Id><IBAN>LT809872649478701594</IBAN></Id><Ccy>EUR</Ccy></Acct><Ntry><Amt Ccy="EUR">28810.91</Amt><CdtDbtInd>DBIT</CdtDbtInd><Sts>INFO</Sts><NtryDtls><TxDtls><Refs><TxId>943400</TxId></Refs><Amt Ccy="EUR">2.48</Amt><CdtDbtInd>CRDT</CdtDbtInd><RltdAgts><DbtrAgt><FinInstnId><BICFI>GEBAFRG3DEH</BICFI></FinInstnId></DbtrAgt><CdtrAgt><FinInstnId><BICFI>DEUTBEB4NDX</BICFI></FinInstnId></CdtrAgt></RltdAgts><RltdDts><AccptncDtTm>2024-04-23T10:42:16</AccptncDtTm><IntrBkSttlmDt>2024-04-23</IntrBkSttlmDt></RltdDts></TxDtls><TxDtls><Refs><TxId>451920</TxId></Refs><Amt Ccy="EUR">10</Amt><CdtDbtInd>CRDT</CdtDbtInd><RltdAgts><DbtrAgt><FinInstnId><BICFI>SWEDFRF9QVG</BICFI></FinInstnId></DbtrAgt><CdtrAgt><FinInstnId><BICFI>DEUTBEB4NDX</BICFI></FinInstnId></CdtrAgt></RltdAgts><RltdDts><AccptncDtTm>2024-04-23T09:46:00</AccptncDtTm><IntrBkSttlmDt>2024-04-23</IntrBkSttlmDt></RltdDts></TxDtls><TxDtls><Refs><TxId>340710</TxId></Refs><Amt Ccy="EUR">10.83</Amt><CdtDbtInd>CRDT</CdtDbtInd><RltdAgts><DbtrAgt><FinInstnId><BICFI>GEBAFRG3DEH</BICFI></FinInstnId></DbtrAgt><CdtrAgt><FinInstnId><BICFI>DEUTBEB4NDX</BICFI></FinInstnId></CdtrAgt></RltdAgts><RltdDts><AccptncDtTm>2024-04-23T09:41:12</AccptncDtTm><IntrBkSttlmDt>2024-04-23</IntrBkSttlmDt></RltdDts></TxDtls><TxDtls><Refs><TxId>730434</TxId></Refs><Amt Ccy="EUR">100</Amt><CdtDbtInd>DBIT</CdtDbtInd><RltdAgts><DbtrAgt><FinInstnId><BICFI>DEUTBEB4NDX</BICFI></FinInstnId></DbtrAgt><CdtrAgt><FinInstnId><BICFI>GEBAFRS0LVF</BICFI></FinInstnId></CdtrAgt></RltdAgts><RltdDts><AccptncDtTm>2024-04-23T09:38:03</AccptncDtTm><IntrBkSttlmDt>2024-04-23</IntrBkSttlmDt></RltdDts></TxDtls><TxDtls><Refs><TxId>110802</TxId></Refs><Amt Ccy="EUR">450</Amt><CdtDbtInd>CRDT</CdtDbtInd><RltdAgts><DbtrAgt><FinInstnId><BICFI>GEBAFRG3DEH</BICFI></FinInstnId></DbtrAgt><CdtrAgt><FinInstnId><BICFI>DEUTBEB4NDX</BICFI></FinInstnId></CdtrAgt></RltdAgts><RltdDts><AccptncDtTm>2024-04-23T09:35:23</AccptncDtTm><IntrBkSttlmDt>2024-04-23</IntrBkSttlmDt></RltdDts></TxDtls><TxDtls><Refs><TxId>370484</TxId></Refs><Amt Ccy="EUR">250</Amt><CdtDbtInd>DBIT</CdtDbtInd><RltdAgts><DbtrAgt><FinInstnId><BICFI>DEUTBEB4NDX</BICFI></FinInstnId></DbtrAgt><CdtrAgt><FinInstnId><BICFI>GEBAFRG3DEH</BICFI></FinInstnId></CdtrAgt></RltdAgts><RltdDts><AccptncDtTm>2024-04-23T09:12:05</AccptncDtTm><IntrBkSttlmDt>2024-04-23</IntrBkSttlmDt></RltdDts></TxDtls><TxDtls><Refs><TxId>454430</TxId></Refs><Amt Ccy="EUR">421.11</Amt><CdtDbtInd>CRDT</CdtDbtInd><RltdAgts><DbtrAgt><FinInstnId><BICFI>FINAFRA3OQE</BICFI></FinInstnId></DbtrAgt><CdtrAgt><FinInstnId><BICFI>SWEDBEM1</BICFI></FinInstnId></CdtrAgt></RltdAgts><RltdDts><AccptncDtTm>2024-04-23T09:01:03</AccptncDtTm><IntrBkSttlmDt>2024-04-23</IntrBkSttlmDt></RltdDts></TxDtls><TxDtls><Refs><TxId>243339</TxId></Refs><Amt Ccy="EUR">.4</Amt><CdtDbtInd>CRDT</CdtDbtInd><RltdAgts><DbtrAgt><FinInstnId><BICFI>FINAFRA3OQE</BICFI></FinInstnId></DbtrAgt><CdtrAgt><FinInstnId><BICFI>SWEDBEM1</BICFI></FinInstnId></CdtrAgt></RltdAgts><RltdDts><AccptncDtTm>2024-04-23T08:47:49</AccptncDtTm><IntrBkSttlmDt>2024-04-23</IntrBkSttlmDt></RltdDts></TxDtls><TxDtls><Refs><TxId>774949</TxId></Refs><Amt Ccy="EUR">100</Amt><CdtDbtInd>CRDT</CdtDbtInd><RltdAgts><DbtrAgt><FinInstnId><BICFI>HBUKFRO7AER</BICFI></FinInstnId></DbtrAgt><CdtrAgt><FinInstnId><BICFI>DEUTBEB4NDX</BICFI></FinInstnId></CdtrAgt></RltdAgts><RltdDts><AccptncDtTm>2024-04-23T08:43:06</AccptncDtTm><IntrBkSttlmDt>2024-04-23</IntrBkSttlmDt></RltdDts></TxDtls><TxDtls><Refs><TxId>758145</TxId></Refs><Amt Ccy="EUR">38</Amt><CdtDbtInd>DBIT</CdtDbtInd><RltdAgts><DbtrAgt><FinInstnId><BICFI>DEUTBEB4NDX</BICFI></FinInstnId></DbtrAgt><CdtrAgt><FinInstnId><BICFI>BNPAFRZ3QJA</BICFI></FinInstnId></CdtrAgt></RltdAgts><RltdDts><AccptncDtTm>2024-04-23T08:21:39</AccptncDtTm><IntrBkSttlmDt>2024-04-23</IntrBkSttlmDt></RltdDts></TxDtls><TxDtls><Refs><TxId>579360</TxId></Refs><Amt Ccy="EUR">18</Amt><CdtDbtInd>DBIT</CdtDbtInd><RltdAgts><DbtrAgt><FinInstnId><BICFI>DEUTBEB4NDX</BICFI></FinInstnId></DbtrAgt><CdtrAgt><FinInstnId><BICFI>ABNADEO7EMJ</BICFI></FinInstnId></CdtrAgt></RltdAgts><RltdDts><AccptncDtTm>2024-04-23T08:21:34</AccptncDtTm><IntrBkSttlmDt>2024-04-23</IntrBkSttlmDt></RltdDts></TxDtls><TxDtls><Refs><TxId>184022</TxId></Refs><Amt Ccy="EUR">60</Amt><CdtDbtInd>DBIT</CdtDbtInd><RltdAgts><DbtrAgt><FinInstnId><BICFI>DEUTBEB4NDX</BICFI></FinInstnId></DbtrAgt><CdtrAgt><FinInstnId><BICFI>HBUKFRJ3JDC</BICFI></FinInstnId></CdtrAgt></RltdAgts><RltdDts><AccptncDtTm>2024-04-23T08:13:41</AccptncDtTm><IntrBkSttlmDt>2024-04-23</IntrBkSttlmDt></RltdDts></TxDtls><TxDtls><Refs><TxId>539497</TxId></Refs><Amt Ccy="EUR">80</Amt><CdtDbtInd>DBIT</CdtDbtInd><RltdAgts><DbtrAgt><FinInstnId><BICFI>DEUTBEB4NDX</BICFI></FinInstnId></DbtrAgt><CdtrAgt><FinInstnId><BICFI>HBUKFRJ3JDC</BICFI></FinInstnId></CdtrAgt></RltdAgts><RltdDts><AccptncDtTm>2024-04-23T08:11:53</AccptncDtTm><IntrBkSttlmDt>2024-04-23</IntrBkSttlmDt></RltdDts></TxDtls><TxDtls><Refs><TxId>915306</TxId></Refs><Amt Ccy="EUR">1702</Amt><CdtDbtInd>DBIT</CdtDbtInd><RltdAgts><DbtrAgt><FinInstnId><BICFI>DEUTBEB4NDX</BICFI></FinInstnId></DbtrAgt><CdtrAgt><FinInstnId><BICFI>GEBAFRG3DEH</BICFI></FinInstnId></CdtrAgt></RltdAgts><RltdDts><AccptncDtTm>2024-04-23T08:06:31</AccptncDtTm><IntrBkSttlmDt>2024-04-23</IntrBkSttlmDt></RltdDts></TxDtls><TxDtls><Refs><TxId>148288</TxId></Refs><Amt Ccy="EUR">30</Amt><CdtDbtInd>DBIT</CdtDbtInd><RltdAgts><DbtrAgt><FinInstnId><BICFI>DEUTBEB4NDX</BICFI></FinInstnId></DbtrAgt><CdtrAgt><FinInstnId><BICFI>ABNAFRF6CPC</BICFI></FinInstnId></CdtrAgt></RltdAgts><RltdDts><AccptncDtTm>2024-04-23T08:06:13</AccptncDtTm><IntrBkSttlmDt>2024-04-23</IntrBkSttlmDt></RltdDts></TxDtls><TxDtls><Refs><TxId>559870</TxId></Refs><Amt Ccy="EUR">150</Amt><CdtDbtInd>DBIT</CdtDbtInd><RltdAgts><DbtrAgt><FinInstnId><BICFI>DEUTBEB4NDX</BICFI></FinInstnId></DbtrAgt><CdtrAgt><FinInstnId><BICFI>GEBAFRI5BAY</BICFI></FinInstnId></CdtrAgt></RltdAgts><RltdDts><AccptncDtTm>2024-04-23T08:05:42</AccptncDtTm><IntrBkSttlmDt>2024-04-23</IntrBkSttlmDt></RltdDts></TxDtls><TxDtls><Refs><TxId>204716</TxId></Refs><Amt Ccy="EUR">300</Amt><CdtDbtInd>DBIT</CdtDbtInd><RltdAgts><DbtrAgt><FinInstnId><BICFI>DEUTBEB4NDX</BICFI></FinInstnId></DbtrAgt><CdtrAgt><FinInstnId><BICFI>BNPAFRZ3QJA</BICFI></FinInstnId></CdtrAgt></RltdAgts><RltdDts><AccptncDtTm>2024-04-23T08:05:35</AccptncDtTm><IntrBkSttlmDt>2024-04-23</IntrBkSttlmDt></RltdDts></TxDtls><TxDtls><Refs><TxId>609895</TxId></Refs><Amt Ccy="EUR">50</Amt><CdtDbtInd>CRDT</CdtDbtInd><RltdAgts><DbtrAgt><FinInstnId><BICFI>ABNAFRG4TMN</BICFI></FinInstnId></DbtrAgt><CdtrAgt><FinInstnId><BICFI>DEUTBEB4NDX</BICFI></FinInstnId></CdtrAgt></RltdAgts><RltdDts><AccptncDtTm>2024-04-23T07:54:12</AccptncDtTm><IntrBkSttlmDt>2024-04-23</IntrBkSttlmDt></RltdDts></TxDtls><TxDtls><Refs><TxId>723279</TxId></Refs><Amt Ccy="EUR">500</Amt><CdtDbtInd>CRDT</CdtDbtInd><RltdAgts><DbtrAgt><FinInstnId><BICFI>HBUKFRO9YIN</BICFI></FinInstnId></DbtrAgt><CdtrAgt><FinInstnId><BICFI>DEUTBEB4NDX</BICFI></FinInstnId></CdtrAgt></RltdAgts><RltdDts><AccptncDtTm>2024-04-23T07:51:37</AccptncDtTm><IntrBkSttlmDt>2024-04-23</IntrBkSttlmDt></RltdDts></TxDtls><TxDtls><Refs><TxId>873703</TxId></Refs><Amt Ccy="EUR">100</Amt><CdtDbtInd>DBIT</CdtDbtInd><RltdAgts><DbtrAgt><FinInstnId><BICFI>DEUTBEB4NDX</BICFI></FinInstnId></DbtrAgt><CdtrAgt><FinInstnId><BICFI>NDEAFRL5QMB</BICFI></FinInstnId></CdtrAgt></RltdAgts><RltdDts><AccptncDtTm>2024-04-23T07:47:55</AccptncDtTm><IntrBkSttlmDt>2024-04-23</IntrBkSttlmDt></RltdDts></TxDtls><TxDtls><Refs><TxId>825464</TxId></Refs><Amt Ccy="EUR">90</Amt><CdtDbtInd>DBIT</CdtDbtInd><RltdAgts><DbtrAgt><FinInstnId><BICFI>DEUTBEB4NDX</BICFI></FinInstnId></DbtrAgt><CdtrAgt><FinInstnId><BICFI>DEUTBEE0KCY</BICFI></FinInstnId></CdtrAgt></RltdAgts><RltdDts><AccptncDtTm>2024-04-23T07:23:29</AccptncDtTm><IntrBkSttlmDt>2024-04-23</IntrBkSttlmDt></RltdDts></TxDtls><TxDtls><Refs><TxId>895474</TxId></Refs><Amt Ccy="EUR">300</Amt><CdtDbtInd>CRDT</CdtDbtInd><RltdAgts><DbtrAgt><FinInstnId><BICFI>BNPAFRZ3QJA</BICFI></FinInstnId></DbtrAgt><CdtrAgt><FinInstnId><BICFI>DEUTBEB4NDX</BICFI></FinInstnId></CdtrAgt></RltdAgts><RltdDts><AccptncDtTm>2024-04-23T07:20:16</AccptncDtTm><IntrBkSttlmDt>2024-04-23</IntrBkSttlmDt></RltdDts></TxDtls><TxDtls><Refs><TxId>577520</TxId></Refs><Amt Ccy="EUR">300</Amt><CdtDbtInd>CRDT</CdtDbtInd><RltdAgts><DbtrAgt><FinInstnId><BICFI>BNPAFRZ3QJA</BICFI></FinInstnId></DbtrAgt><CdtrAgt><FinInstnId><BICFI>DEUTBEB4NDX</BICFI></FinInstnId></CdtrAgt></RltdAgts><RltdDts><AccptncDtTm>2024-04-23T07:18:29</AccptncDtTm><IntrBkSttlmDt>2024-04-23</IntrBkSttlmDt></RltdDts></TxDtls><TxDtls><Refs><TxId>979615</TxId></Refs><Amt Ccy="EUR">240</Amt><CdtDbtInd>CRDT</CdtDbtInd><RltdAgts><DbtrAgt><FinInstnId><BICFI>HBUKFRJ3JDC</BICFI></FinInstnId></DbtrAgt><CdtrAgt><FinInstnId><BICFI>DEUTBEB4NDX</BICFI></FinInstnId></CdtrAgt></RltdAgts><RltdDts><AccptncDtTm>2024-04-23T06:11:17</AccptncDtTm><IntrBkSttlmDt>2024-04-23</IntrBkSttlmDt></RltdDts></TxDtls><TxDtls><Refs><TxId>207414</TxId></Refs><Amt Ccy="EUR">15</Amt><CdtDbtInd>CRDT</CdtDbtInd><RltdAgts><DbtrAgt><FinInstnId><BICFI>GEBAFRZ1XAW</BICFI></FinInstnId></DbtrAgt><CdtrAgt><FinInstnId><BICFI>DEUTBEB4NDX</BICFI></FinInstnId></CdtrAgt></RltdAgts><RltdDts><AccptncDtTm>2024-04-23T05:56:51</AccptncDtTm><IntrBkSttlmDt>2024-04-23</IntrBkSttlmDt></RltdDts></TxDtls><TxDtls><Refs><TxId>196939</TxId></Refs><Amt Ccy="EUR">50</Amt><CdtDbtInd>DBIT</CdtDbtInd><RltdAgts><DbtrAgt><FinInstnId><BICFI>DEUTBEB4NDX</BICFI></FinInstnId></DbtrAgt><CdtrAgt><FinInstnId><BICFI>ABNAFRK3RDO</BICFI></FinInstnId></CdtrAgt></RltdAgts><RltdDts><AccptncDtTm>2024-04-23T05:51:27</AccptncDtTm><IntrBkSttlmDt>2024-04-23</IntrBkSttlmDt></RltdDts></TxDtls><TxDtls><Refs><TxId>377610</TxId></Refs><Amt Ccy="EUR">20</Amt><CdtDbtInd>DBIT</CdtDbtInd><RltdAgts><DbtrAgt><FinInstnId><BICFI>DEUTBEB4NDX</BICFI></FinInstnId></DbtrAgt><CdtrAgt><FinInstnId><BICFI>GEBAFRG3DEH</BICFI></FinInstnId></CdtrAgt></RltdAgts><RltdDts><AccptncDtTm>2024-04-23T05:26:10</AccptncDtTm><IntrBkSttlmDt>2024-04-23</IntrBkSttlmDt></RltdDts></TxDtls><TxDtls><Refs><TxId>253689</TxId></Refs><Amt Ccy="EUR">100</Amt><CdtDbtInd>CRDT</CdtDbtInd><RltdAgts><DbtrAgt><FinInstnId><BICFI>GEBAFRG3DEH</BICFI></FinInstnId></DbtrAgt><CdtrAgt><FinInstnId><BICFI>DEUTBEB4NDX</BICFI></FinInstnId></CdtrAgt></RltdAgts><RltdDts><AccptncDtTm>2024-04-23T05:19:36</AccptncDtTm><IntrBkSttlmDt>2024-04-23</IntrBkSttlmDt></RltdDts></TxDtls><TxDtls><Refs><TxId>459444</TxId></Refs><Amt Ccy="EUR">2</Amt><CdtDbtInd>CRDT</CdtDbtInd><RltdAgts><DbtrAgt><FinInstnId><BICFI>HBUKFRJ3JDC</BICFI></FinInstnId></DbtrAgt><CdtrAgt><FinInstnId><BICFI>DEUTBEB4NDX</BICFI></FinInstnId></CdtrAgt></RltdAgts><RltdDts><AccptncDtTm>2024-04-23T04:01:47</AccptncDtTm><IntrBkSttlmDt>2024-04-23</IntrBkSttlmDt></RltdDts></TxDtls><TxDtls><Refs><TxId>765314</TxId></Refs><Amt Ccy="EUR">9</Amt><CdtDbtInd>DBIT</CdtDbtInd><RltdAgts><DbtrAgt><FinInstnId><BICFI>DEUTBEB4NDX</BICFI></FinInstnId></DbtrAgt><CdtrAgt><FinInstnId><BICFI>NDEAFRR1AZT</BICFI></FinInstnId></CdtrAgt></RltdAgts><RltdDts><AccptncDtTm>2024-04-23T01:27:22</AccptncDtTm><IntrBkSttlmDt>2024-04-23</IntrBkSttlmDt></RltdDts></TxDtls><TxDtls><Refs><TxId>197711</TxId></Refs><Amt Ccy="EUR">20</Amt><CdtDbtInd>DBIT</CdtDbtInd><RltdAgts><DbtrAgt><FinInstnId><BICFI>DEUTBEB4NDX</BICFI></FinInstnId></DbtrAgt><CdtrAgt><FinInstnId><BICFI>HBUKFRO7AER</BICFI></FinInstnId></CdtrAgt></RltdAgts><RltdDts><AccptncDtTm>2024-04-23T00:25:34</AccptncDtTm><IntrBkSttlmDt>2024-04-23</IntrBkSttlmDt></RltdDts></TxDtls><TxDtls><Refs><TxId>461221</TxId></Refs><Amt Ccy="EUR">13797</Amt><CdtDbtInd>DBIT</CdtDbtInd><RltdAgts><DbtrAgt><FinInstnId><BICFI>DEUTBEB4NDX</BICFI></FinInstnId></DbtrAgt><CdtrAgt><FinInstnId><BICFI>HBUKLUA8SWI</BICFI></FinInstnId></CdtrAgt></RltdAgts><RltdDts><AccptncDtTm>2024-04-23T00:25:26</AccptncDtTm><IntrBkSttlmDt>2024-04-23</IntrBkSttlmDt></RltdDts></TxDtls><TxDtls><Refs><TxId>502021</TxId></Refs><Amt Ccy="EUR">13500</Amt><CdtDbtInd>DBIT</CdtDbtInd><RltdAgts><DbtrAgt><FinInstnId><BICFI>DEUTBEB4NDX</BICFI></FinInstnId></DbtrAgt><CdtrAgt><FinInstnId><BICFI>HBUKLUA8SWI</BICFI></FinInstnId></CdtrAgt></RltdAgts><RltdDts><AccptncDtTm>2024-04-23T00:23:01</AccptncDtTm><IntrBkSttlmDt>2024-04-23</IntrBkSttlmDt></RltdDts></TxDtls><TxDtls><Refs><TxId>181834</TxId></Refs><Amt Ccy="EUR">40</Amt><CdtDbtInd>CRDT</CdtDbtInd><RltdAgts><DbtrAgt><FinInstnId><BICFI>FINADEG7XAL</BICFI></FinInstnId></DbtrAgt><CdtrAgt><FinInstnId><BICFI>DEUTBEB4NDX</BICFI></FinInstnId></CdtrAgt></RltdAgts><RltdDts><AccptncDtTm>2024-04-23T00:06:05</AccptncDtTm><IntrBkSttlmDt>2024-04-23</IntrBkSttlmDt></RltdDts></TxDtls><TxDtls><Refs><TxId>991743</TxId></Refs><Amt Ccy="EUR">10</Amt><CdtDbtInd>CRDT</CdtDbtInd><RltdAgts><DbtrAgt><FinInstnId><BICFI>GEBAFRG3DEH</BICFI></FinInstnId></DbtrAgt><CdtrAgt><FinInstnId><BICFI>DEUTBEB4NDX</BICFI></FinInstnId></CdtrAgt></RltdAgts><RltdDts><AccptncDtTm>2024-04-23T00:04:21</AccptncDtTm><IntrBkSttlmDt>2024-04-23</IntrBkSttlmDt></RltdDts></TxDtls><TxDtls><Refs><TxId>525168</TxId></Refs><Amt Ccy="EUR">300</Amt><CdtDbtInd>DBIT</CdtDbtInd><RltdAgts><DbtrAgt><FinInstnId><BICFI>DEUTBEB4NDX</BICFI></FinInstnId></DbtrAgt><CdtrAgt><FinInstnId><BICFI>FINAFRI7CQJ</BICFI></FinInstnId></CdtrAgt></RltdAgts><RltdDts><AccptncDtTm>2024-04-22T23:47:14</AccptncDtTm><IntrBkSttlmDt>2024-04-23</IntrBkSttlmDt></RltdDts></TxDtls><TxDtls><Refs><TxId>600995</TxId></Refs><Amt Ccy="EUR">35.5</Amt><CdtDbtInd>CRDT</CdtDbtInd><RltdAgts><DbtrAgt><FinInstnId><BICFI>GEBAFRG3DEH</BICFI></FinInstnId></DbtrAgt><CdtrAgt><FinInstnId><BICFI>DEUTBEB4NDX</BICFI></FinInstnId></CdtrAgt></RltdAgts><RltdDts><AccptncDtTm>2024-04-22T22:56:56</AccptncDtTm><IntrBkSttlmDt>2024-04-23</IntrBkSttlmDt></RltdDts></TxDtls><TxDtls><Refs><TxId>107010</TxId></Refs><Amt Ccy="EUR">4595</Amt><CdtDbtInd>CRDT</CdtDbtInd><RltdAgts><DbtrAgt><FinInstnId><BICFI>FINALTJ2RVE</BICFI></FinInstnId></DbtrAgt><CdtrAgt><FinInstnId><BICFI>DEUTBEB4NDX</BICFI></FinInstnId></CdtrAgt></RltdAgts><RltdDts><AccptncDtTm>2024-04-22T22:20:58</AccptncDtTm><IntrBkSttlmDt>2024-04-23</IntrBkSttlmDt></RltdDts></TxDtls><TxDtls><Refs><TxId>498774</TxId></Refs><Amt Ccy="EUR">200</Amt><CdtDbtInd>DBIT</CdtDbtInd><RltdAgts><DbtrAgt><FinInstnId><BICFI>DEUTBEB4NDX</BICFI></FinInstnId></DbtrAgt><CdtrAgt><FinInstnId><BICFI>HBUKFRR0SBV</BICFI></FinInstnId></CdtrAgt></RltdAgts><RltdDts><AccptncDtTm>2024-04-22T22:15:50</AccptncDtTm><IntrBkSttlmDt>2024-04-23</IntrBkSttlmDt></RltdDts></TxDtls><TxDtls><Refs><TxId>257059</TxId></Refs><Amt Ccy="EUR">300</Amt><CdtDbtInd>CRDT</CdtDbtInd><RltdAgts><DbtrAgt><FinInstnId><BICFI>GEBAFRI5BAY</BICFI></FinInstnId></DbtrAgt><CdtrAgt><FinInstnId><BICFI>DEUTBEB4NDX</BICFI></FinInstnId></CdtrAgt></RltdAgts><RltdDts><AccptncDtTm>2024-04-23T21:45:25</AccptncDtTm><IntrBkSttlmDt>2024-04-23</IntrBkSttlmDt></RltdDts></TxDtls><TxDtls><Refs><TxId>440083</TxId></Refs><Amt Ccy="EUR">2500</Amt><CdtDbtInd>CRDT</CdtDbtInd><RltdAgts><DbtrAgt><FinInstnId><BICFI>GEBAFRG3DEH</BICFI></FinInstnId></DbtrAgt><CdtrAgt><FinInstnId><BICFI>DEUTBEB4NDX</BICFI></FinInstnId></CdtrAgt></RltdAgts><RltdDts><AccptncDtTm>2024-04-23T21:38:05</AccptncDtTm><IntrBkSttlmDt>2024-04-23</IntrBkSttlmDt></RltdDts></TxDtls><TxDtls><Refs><TxId>602478</TxId></Refs><Amt Ccy="EUR">100</Amt><CdtDbtInd>CRDT</CdtDbtInd><RltdAgts><DbtrAgt><FinInstnId><BICFI>HBUKFRO7AER</BICFI></FinInstnId></DbtrAgt><CdtrAgt><FinInstnId><BICFI>DEUTBEB4NDX</BICFI></FinInstnId></CdtrAgt></RltdAgts><RltdDts><AccptncDtTm>2024-04-23T21:35:05</AccptncDtTm><IntrBkSttlmDt>2024-04-23</IntrBkSttlmDt></RltdDts></TxDtls><TxDtls><Refs><TxId>529155</TxId></Refs><Amt Ccy="EUR">200</Amt><CdtDbtInd>DBIT</CdtDbtInd><RltdAgts><DbtrAgt><FinInstnId><BICFI>DEUTBEB4NDX</BICFI></FinInstnId></DbtrAgt><CdtrAgt><FinInstnId><BICFI>INGBBER8XUT</BICFI></FinInstnId></CdtrAgt></RltdAgts><RltdDts><AccptncDtTm>2024-04-23T21:26:07</AccptncDtTm><IntrBkSttlmDt>2024-04-23</IntrBkSttlmDt></RltdDts></TxDtls><TxDtls><Refs><TxId>229077</TxId></Refs><Amt Ccy="EUR">600</Amt><CdtDbtInd>DBIT</CdtDbtInd><RltdAgts><DbtrAgt><FinInstnId><BICFI>DEUTBEB4NDX</BICFI></FinInstnId></DbtrAgt><CdtrAgt><FinInstnId><BICFI>DEUTGRZ5CVP</BICFI></FinInstnId></CdtrAgt></RltdAgts><RltdDts><AccptncDtTm>2024-04-23T20:13:57</AccptncDtTm><IntrBkSttlmDt>2024-04-23</IntrBkSttlmDt></RltdDts></TxDtls><TxDtls><Refs><TxId>907423</TxId></Refs><Amt Ccy="EUR">200</Amt><CdtDbtInd>CRDT</CdtDbtInd><RltdAgts><DbtrAgt><FinInstnId><BICFI>GEBAFRG3DEH</BICFI></FinInstnId></DbtrAgt><CdtrAgt><FinInstnId><BICFI>DEUTBEB4NDX</BICFI></FinInstnId></CdtrAgt></RltdAgts><RltdDts><AccptncDtTm>2024-04-23T19:53:43</AccptncDtTm><IntrBkSttlmDt>2024-04-23</IntrBkSttlmDt></RltdDts></TxDtls><TxDtls><Refs><TxId>676911</TxId></Refs><Amt Ccy="EUR">100</Amt><CdtDbtInd>DBIT</CdtDbtInd><RltdAgts><DbtrAgt><FinInstnId><BICFI>DEUTBEB4NDX</BICFI></FinInstnId></DbtrAgt><CdtrAgt><FinInstnId><BICFI>GEBAFRI5BAY</BICFI></FinInstnId></CdtrAgt></RltdAgts><RltdDts><AccptncDtTm>2024-04-23T19:52:56</AccptncDtTm><IntrBkSttlmDt>2024-04-23</IntrBkSttlmDt></RltdDts></TxDtls><TxDtls><Refs><TxId>665738</TxId></Refs><Amt Ccy="EUR">30</Amt><CdtDbtInd>CRDT</CdtDbtInd><RltdAgts><DbtrAgt><FinInstnId><BICFI>HBUKFRO7AER</BICFI></FinInstnId></DbtrAgt><CdtrAgt><FinInstnId><BICFI>DEUTBEB4NDX</BICFI></FinInstnId></CdtrAgt></RltdAgts><RltdDts><AccptncDtTm>2024-04-23T19:42:49</AccptncDtTm><IntrBkSttlmDt>2024-04-23</IntrBkSttlmDt></RltdDts></TxDtls><TxDtls><Refs><TxId>426392</TxId></Refs><Amt Ccy="EUR">400</Amt><CdtDbtInd>CRDT</CdtDbtInd><RltdAgts><DbtrAgt><FinInstnId><BICFI>NDEAFRZ9ZQR</BICFI></FinInstnId></DbtrAgt><CdtrAgt><FinInstnId><BICFI>DEUTBEB4NDX</BICFI></FinInstnId></CdtrAgt></RltdAgts><RltdDts><AccptncDtTm>2024-04-23T19:26:20</AccptncDtTm><IntrBkSttlmDt>2024-04-23</IntrBkSttlmDt></RltdDts></TxDtls><TxDtls><Refs><TxId>770725</TxId></Refs><Amt Ccy="EUR">2</Amt><CdtDbtInd>DBIT</CdtDbtInd><RltdAgts><DbtrAgt><FinInstnId><BICFI>DEUTBEB4NDX</BICFI></FinInstnId></DbtrAgt><CdtrAgt><FinInstnId><BICFI>INGBFRW3IUA</BICFI></FinInstnId></CdtrAgt></RltdAgts><RltdDts><AccptncDtTm>2024-04-23T19:19:59</AccptncDtTm><IntrBkSttlmDt>2024-04-23</IntrBkSttlmDt></RltdDts></TxDtls><TxDtls><Refs><TxId>487767</TxId></Refs><Amt Ccy="EUR">100</Amt><CdtDbtInd>DBIT</CdtDbtInd><RltdAgts><DbtrAgt><FinInstnId><BICFI>DEUTBEB4NDX</BICFI></FinInstnId></DbtrAgt><CdtrAgt><FinInstnId><BICFI>BKAUFRY8WYG</BICFI></FinInstnId></CdtrAgt></RltdAgts><RltdDts><AccptncDtTm>2024-04-23T19:18:27</AccptncDtTm><IntrBkSttlmDt>2024-04-23</IntrBkSttlmDt></RltdDts></TxDtls><TxDtls><Refs><TxId>651876</TxId></Refs><Amt Ccy="EUR">1000</Amt><CdtDbtInd>CRDT</CdtDbtInd><RltdAgts><DbtrAgt><FinInstnId><BICFI>HBUKFRR0SBV</BICFI></FinInstnId></DbtrAgt><CdtrAgt><FinInstnId><BICFI>SWEDBEM1</BICFI></FinInstnId></CdtrAgt></RltdAgts><RltdDts><AccptncDtTm>2024-04-23T18:37:42</AccptncDtTm><IntrBkSttlmDt>2024-04-23</IntrBkSttlmDt></RltdDts></TxDtls><TxDtls><Refs><TxId>185772</TxId></Refs><Amt Ccy="EUR">1000</Amt><CdtDbtInd>CRDT</CdtDbtInd><RltdAgts><DbtrAgt><FinInstnId><BICFI>HBUKFRR0SBV</BICFI></FinInstnId></DbtrAgt><CdtrAgt><FinInstnId><BICFI>SWEDBEM1</BICFI></FinInstnId></CdtrAgt></RltdAgts><RltdDts><AccptncDtTm>2024-04-23T18:37:33</AccptncDtTm><IntrBkSttlmDt>2024-04-23</IntrBkSttlmDt></RltdDts></TxDtls><TxDtls><Refs><TxId>657250</TxId></Refs><Amt Ccy="EUR">50</Amt><CdtDbtInd>CRDT</CdtDbtInd><RltdAgts><DbtrAgt><FinInstnId><BICFI>HBUKFRO7AER</BICFI></FinInstnId></DbtrAgt><CdtrAgt><FinInstnId><BICFI>DEUTBEB4NDX</BICFI></FinInstnId></CdtrAgt></RltdAgts><RltdDts><AccptncDtTm>2024-04-23T18:28:41</AccptncDtTm><IntrBkSttlmDt>2024-04-23</IntrBkSttlmDt></RltdDts></TxDtls><TxDtls><Refs><TxId>438246</TxId></Refs><Amt Ccy="EUR">384.02</Amt><CdtDbtInd>CRDT</CdtDbtInd><RltdAgts><DbtrAgt><FinInstnId><BICFI>FINAFRA3OQE</BICFI></FinInstnId></DbtrAgt><CdtrAgt><FinInstnId><BICFI>SWEDBEM1</BICFI></FinInstnId></CdtrAgt></RltdAgts><RltdDts><AccptncDtTm>2024-04-23T18:23:39</AccptncDtTm><IntrBkSttlmDt>2024-04-23</IntrBkSttlmDt></RltdDts></TxDtls><TxDtls><Refs><TxId>251293</TxId></Refs><Amt Ccy="EUR">100</Amt><CdtDbtInd>CRDT</CdtDbtInd><RltdAgts><DbtrAgt><FinInstnId><BICFI>GEBAFRG3DEH</BICFI></FinInstnId></DbtrAgt><CdtrAgt><FinInstnId><BICFI>DEUTBEB4NDX</BICFI></FinInstnId></CdtrAgt></RltdAgts><RltdDts><AccptncDtTm>2024-04-23T18:11:18</AccptncDtTm><IntrBkSttlmDt>2024-04-23</IntrBkSttlmDt></RltdDts></TxDtls><TxDtls><Refs><TxId>424277</TxId></Refs><Amt Ccy="EUR">64</Amt><CdtDbtInd>DBIT</CdtDbtInd><RltdAgts><DbtrAgt><FinInstnId><BICFI>DEUTBEB4NDX</BICFI></FinInstnId></DbtrAgt><CdtrAgt><FinInstnId><BICFI>GEBAFRZ1XAW</BICFI></FinInstnId></CdtrAgt></RltdAgts><RltdDts><AccptncDtTm>2024-04-23T18:02:12</AccptncDtTm><IntrBkSttlmDt>2024-04-23</IntrBkSttlmDt></RltdDts></TxDtls><TxDtls><Refs><TxId>904924</TxId></Refs><Amt Ccy="EUR">35</Amt><CdtDbtInd>CRDT</CdtDbtInd><RltdAgts><DbtrAgt><FinInstnId><BICFI>KREDFRC8QER</BICFI></FinInstnId></DbtrAgt><CdtrAgt><FinInstnId><BICFI>DEUTBEB4NDX</BICFI></FinInstnId></CdtrAgt></RltdAgts><RltdDts><AccptncDtTm>2024-04-23T17:50:55</AccptncDtTm><IntrBkSttlmDt>2024-04-23</IntrBkSttlmDt></RltdDts></TxDtls><TxDtls><Refs><TxId>807544</TxId></Refs><Amt Ccy="EUR">49.2</Amt><CdtDbtInd>DBIT</CdtDbtInd><RltdAgts><DbtrAgt><FinInstnId><BICFI>DEUTBEB4NDX</BICFI></FinInstnId></DbtrAgt><CdtrAgt><FinInstnId><BICFI>SWEDFRF3EPP</BICFI></FinInstnId></CdtrAgt></RltdAgts><RltdDts><AccptncDtTm>2024-04-23T17:25:54</AccptncDtTm><IntrBkSttlmDt>2024-04-23</IntrBkSttlmDt></RltdDts></TxDtls><TxDtls><Refs><TxId>382609</TxId></Refs><Amt Ccy="EUR">50</Amt><CdtDbtInd>DBIT</CdtDbtInd><RltdAgts><DbtrAgt><FinInstnId><BICFI>DEUTBEB4NDX</BICFI></FinInstnId></DbtrAgt><CdtrAgt><FinInstnId><BICFI>HBUKDEE6ODA</BICFI></FinInstnId></CdtrAgt></RltdAgts><RltdDts><AccptncDtTm>2024-04-23T17:12:52</AccptncDtTm><IntrBkSttlmDt>2024-04-23</IntrBkSttlmDt></RltdDts></TxDtls><TxDtls><Refs><TxId>799332</TxId></Refs><Amt Ccy="EUR">50</Amt><CdtDbtInd>CRDT</CdtDbtInd><RltdAgts><DbtrAgt><FinInstnId><BICFI>KREDFRX6UKD</BICFI></FinInstnId></DbtrAgt><CdtrAgt><FinInstnId><BICFI>DEUTBEB4NDX</BICFI></FinInstnId></CdtrAgt></RltdAgts><RltdDts><AccptncDtTm>2024-04-23T17:04:43</AccptncDtTm><IntrBkSttlmDt>2024-04-23</IntrBkSttlmDt></RltdDts></TxDtls><TxDtls><Refs><TxId>466176</TxId></Refs><Amt Ccy="EUR">25</Amt><CdtDbtInd>CRDT</CdtDbtInd><RltdAgts><DbtrAgt><FinInstnId><BICFI>GEBAFRG3DEH</BICFI></FinInstnId></DbtrAgt><CdtrAgt><FinInstnId><BICFI>DEUTBEB4NDX</BICFI></FinInstnId></CdtrAgt></RltdAgts><RltdDts><AccptncDtTm>2024-04-23T17:03:39</AccptncDtTm><IntrBkSttlmDt>2024-04-23</IntrBkSttlmDt></RltdDts></TxDtls><TxDtls><Refs><TxId>443636</TxId></Refs><Amt Ccy="EUR">100</Amt><CdtDbtInd>DBIT</CdtDbtInd><RltdAgts><DbtrAgt><FinInstnId><BICFI>DEUTBEB4NDX</BICFI></FinInstnId></DbtrAgt><CdtrAgt><FinInstnId><BICFI>KREDFRB4EHO</BICFI></FinInstnId></CdtrAgt></RltdAgts><RltdDts><AccptncDtTm>2024-04-23T17:03:11</AccptncDtTm><IntrBkSttlmDt>2024-04-23</IntrBkSttlmDt></RltdDts></TxDtls><TxDtls><Refs><TxId>747506</TxId></Refs><Amt Ccy="EUR">108.22</Amt><CdtDbtInd>CRDT</CdtDbtInd><RltdAgts><DbtrAgt><FinInstnId><BICFI>GEBAFRG3DEH</BICFI></FinInstnId></DbtrAgt><CdtrAgt><FinInstnId><BICFI>DEUTBEB4NDX</BICFI></FinInstnId></CdtrAgt></RltdAgts><RltdDts><AccptncDtTm>2024-04-23T17:02:53</AccptncDtTm><IntrBkSttlmDt>2024-04-23</IntrBkSttlmDt></RltdDts></TxDtls><TxDtls><Refs><TxId>776610</TxId></Refs><Amt Ccy="EUR">50</Amt><CdtDbtInd>DBIT</CdtDbtInd><RltdAgts><DbtrAgt><FinInstnId><BICFI>DEUTBEB4NDX</BICFI></FinInstnId></DbtrAgt><CdtrAgt><FinInstnId><BICFI>KREDFRB4EHO</BICFI></FinInstnId></CdtrAgt></RltdAgts><RltdDts><AccptncDtTm>2024-04-23T17:02:07</AccptncDtTm><IntrBkSttlmDt>2024-04-23</IntrBkSttlmDt></RltdDts></TxDtls><TxDtls><Refs><TxId>477549</TxId></Refs><Amt Ccy="EUR">107.83</Amt><CdtDbtInd>CRDT</CdtDbtInd><RltdAgts><DbtrAgt><FinInstnId><BICFI>GEBAFRG3DEH</BICFI></FinInstnId></DbtrAgt><CdtrAgt><FinInstnId><BICFI>DEUTBEB4NDX</BICFI></FinInstnId></CdtrAgt></RltdAgts><RltdDts><AccptncDtTm>2024-04-23T16:40:54</AccptncDtTm><IntrBkSttlmDt>2024-04-23</IntrBkSttlmDt></RltdDts></TxDtls><TxDtls><Refs><TxId>294202</TxId></Refs><Amt Ccy="EUR">50</Amt><CdtDbtInd>DBIT</CdtDbtInd><RltdAgts><DbtrAgt><FinInstnId><BICFI>DEUTBEB4NDX</BICFI></FinInstnId></DbtrAgt><CdtrAgt><FinInstnId><BICFI>GEBAFRZ1XAW</BICFI></FinInstnId></CdtrAgt></RltdAgts><RltdDts><AccptncDtTm>2024-04-23T16:36:06</AccptncDtTm><IntrBkSttlmDt>2024-04-23</IntrBkSttlmDt></RltdDts></TxDtls><TxDtls><Refs><TxId>119795</TxId></Refs><Amt Ccy="EUR">225</Amt><CdtDbtInd>CRDT</CdtDbtInd><RltdAgts><DbtrAgt><FinInstnId><BICFI>GEBAFRM3IRH</BICFI></FinInstnId></DbtrAgt><CdtrAgt><FinInstnId><BICFI>DEUTBEB4NDX</BICFI></FinInstnId></CdtrAgt></RltdAgts><RltdDts><AccptncDtTm>2024-04-23T16:23:43</AccptncDtTm><IntrBkSttlmDt>2024-04-23</IntrBkSttlmDt></RltdDts></TxDtls><TxDtls><Refs><TxId>441893</TxId></Refs><Amt Ccy="EUR">25</Amt><CdtDbtInd>DBIT</CdtDbtInd><RltdAgts><DbtrAgt><FinInstnId><BICFI>DEUTBEB4NDX</BICFI></FinInstnId></DbtrAgt><CdtrAgt><FinInstnId><BICFI>ABNAFRV6YYW</BICFI></FinInstnId></CdtrAgt></RltdAgts><RltdDts><AccptncDtTm>2024-04-23T16:18:39</AccptncDtTm><IntrBkSttlmDt>2024-04-23</IntrBkSttlmDt></RltdDts></TxDtls><TxDtls><Refs><TxId>361362</TxId></Refs><Amt Ccy="EUR">101</Amt><CdtDbtInd>CRDT</CdtDbtInd><RltdAgts><DbtrAgt><FinInstnId><BICFI>INGBFRW3IUA</BICFI></FinInstnId></DbtrAgt><CdtrAgt><FinInstnId><BICFI>DEUTBEB4NDX</BICFI></FinInstnId></CdtrAgt></RltdAgts><RltdDts><AccptncDtTm>2024-04-23T16:13:55</AccptncDtTm><IntrBkSttlmDt>2024-04-23</IntrBkSttlmDt></RltdDts></TxDtls><TxDtls><Refs><TxId>312542</TxId></Refs><Amt Ccy="EUR">50</Amt><CdtDbtInd>CRDT</CdtDbtInd><RltdAgts><DbtrAgt><FinInstnId><BICFI>HBUKFRG2MJQ</BICFI></FinInstnId></DbtrAgt><CdtrAgt><FinInstnId><BICFI>DEUTBEB4NDX</BICFI></FinInstnId></CdtrAgt></RltdAgts><RltdDts><AccptncDtTm>2024-04-23T16:05:33</AccptncDtTm><IntrBkSttlmDt>2024-04-23</IntrBkSttlmDt></RltdDts></TxDtls><TxDtls><Refs><TxId>610822</TxId></Refs><Amt Ccy="EUR">20</Amt><CdtDbtInd>CRDT</CdtDbtInd><RltdAgts><DbtrAgt><FinInstnId><BICFI>GEBAFRG3DEH</BICFI></FinInstnId></DbtrAgt><CdtrAgt><FinInstnId><BICFI>DEUTBEB4NDX</BICFI></FinInstnId></CdtrAgt></RltdAgts><RltdDts><AccptncDtTm>2024-04-23T10:41:34</AccptncDtTm><IntrBkSttlmDt>2024-04-23</IntrBkSttlmDt></RltdDts></TxDtls><TxDtls><Refs><TxId>336371</TxId></Refs><Amt Ccy="EUR">9</Amt><CdtDbtInd>DBIT</CdtDbtInd><RltdAgts><DbtrAgt><FinInstnId><BICFI>DEUTBEB4NDX</BICFI></FinInstnId></DbtrAgt><CdtrAgt><FinInstnId><BICFI>GEBAFRI5BAY</BICFI></FinInstnId></CdtrAgt></RltdAgts><RltdDts><AccptncDtTm>2024-04-23T10:23:55</AccptncDtTm><IntrBkSttlmDt>2024-04-23</IntrBkSttlmDt></RltdDts></TxDtls><TxDtls><Refs><TxId>152834</TxId></Refs><Amt Ccy="EUR">8.85</Amt><CdtDbtInd>CRDT</CdtDbtInd><RltdAgts><DbtrAgt><FinInstnId><BICFI>GEBAFRG3DEH</BICFI></FinInstnId></DbtrAgt><CdtrAgt><FinInstnId><BICFI>DEUTBEB4NDX</BICFI></FinInstnId></CdtrAgt></RltdAgts><RltdDts><AccptncDtTm>2024-04-23T10:21:08</AccptncDtTm><IntrBkSttlmDt>2024-04-23</IntrBkSttlmDt></RltdDts></TxDtls><TxDtls><Refs><TxId>950312</TxId></Refs><Amt Ccy="EUR">140</Amt><CdtDbtInd>CRDT</CdtDbtInd><RltdAgts><DbtrAgt><FinInstnId><BICFI>FINAFRC2SMS</BICFI></FinInstnId></DbtrAgt><CdtrAgt><FinInstnId><BICFI>DEUTBEB4NDX</BICFI></FinInstnId></CdtrAgt></RltdAgts><RltdDts><AccptncDtTm>2024-04-23T10:06:37</AccptncDtTm><IntrBkSttlmDt>2024-04-23</IntrBkSttlmDt></RltdDts></TxDtls><TxDtls><Refs><TxId>720593</TxId></Refs><Amt Ccy="EUR">400</Amt><CdtDbtInd>CRDT</CdtDbtInd><RltdAgts><DbtrAgt><FinInstnId><BICFI>RABOFRA8BGE</BICFI></FinInstnId></DbtrAgt><CdtrAgt><FinInstnId><BICFI>DEUTBEB4NDX</BICFI></FinInstnId></CdtrAgt></RltdAgts><RltdDts><AccptncDtTm>2024-04-23T10:06:20</AccptncDtTm><IntrBkSttlmDt>2024-04-23</IntrBkSttlmDt></RltdDts></TxDtls><TxDtls><Refs><TxId>357539</TxId></Refs><Amt Ccy="EUR">25</Amt><CdtDbtInd>CRDT</CdtDbtInd><RltdAgts><DbtrAgt><FinInstnId><BICFI>SWEDFRM3HWA</BICFI></FinInstnId></DbtrAgt><CdtrAgt><FinInstnId><BICFI>DEUTBEB4NDX</BICFI></FinInstnId></CdtrAgt></RltdAgts><RltdDts><AccptncDtTm>2024-04-23T10:03:32</AccptncDtTm><IntrBkSttlmDt>2024-04-23</IntrBkSttlmDt></RltdDts></TxDtls><TxDtls><Refs><TxId>109214</TxId></Refs><Amt Ccy="EUR">2500</Amt><CdtDbtInd>DBIT</CdtDbtInd><RltdAgts><DbtrAgt><FinInstnId><BICFI>DEUTBEB4NDX</BICFI></FinInstnId></DbtrAgt><CdtrAgt><FinInstnId><BICFI>INGBBER8XUT</BICFI></FinInstnId></CdtrAgt></RltdAgts><RltdDts><AccptncDtTm>2024-04-23T10:01:13</AccptncDtTm><IntrBkSttlmDt>2024-04-23</IntrBkSttlmDt></RltdDts></TxDtls><TxDtls><Refs><TxId>959525</TxId></Refs><Amt Ccy="EUR">500</Amt><CdtDbtInd>CRDT</CdtDbtInd><RltdAgts><DbtrAgt><FinInstnId><BICFI>GEBAFRG3DEH</BICFI></FinInstnId></DbtrAgt><CdtrAgt><FinInstnId><BICFI>DEUTBEB4NDX</BICFI></FinInstnId></CdtrAgt></RltdAgts><RltdDts><AccptncDtTm>2024-04-23T09:56:25</AccptncDtTm><IntrBkSttlmDt>2024-04-23</IntrBkSttlmDt></RltdDts></TxDtls><TxDtls><Refs><TxId>278791</TxId></Refs><Amt Ccy="EUR">2500</Amt><CdtDbtInd>DBIT</CdtDbtInd><RltdAgts><DbtrAgt><FinInstnId><BICFI>DEUTBEB4NDX</BICFI></FinInstnId></DbtrAgt><CdtrAgt><FinInstnId><BICFI>INGBBER8XUT</BICFI></FinInstnId></CdtrAgt></RltdAgts><RltdDts><AccptncDtTm>2024-04-23T09:54:10</AccptncDtTm><IntrBkSttlmDt>2024-04-23</IntrBkSttlmDt></RltdDts></TxDtls><TxDtls><Refs><TxId>926797</TxId></Refs><Amt Ccy="EUR">80</Amt><CdtDbtInd>CRDT</CdtDbtInd><RltdAgts><DbtrAgt><FinInstnId><BICFI>HBUKFRO7AER</BICFI></FinInstnId></DbtrAgt><CdtrAgt><FinInstnId><BICFI>DEUTBEB4NDX</BICFI></FinInstnId></CdtrAgt></RltdAgts><RltdDts><AccptncDtTm>2024-04-23T15:59:52</AccptncDtTm><IntrBkSttlmDt>2024-04-23</IntrBkSttlmDt></RltdDts></TxDtls><TxDtls><Refs><TxId>789592</TxId></Refs><Amt Ccy="EUR">300</Amt><CdtDbtInd>CRDT</CdtDbtInd><RltdAgts><DbtrAgt><FinInstnId><BICFI>HBUKFRO7AER</BICFI></FinInstnId></DbtrAgt><CdtrAgt><FinInstnId><BICFI>DEUTBEB4NDX</BICFI></FinInstnId></CdtrAgt></RltdAgts><RltdDts><AccptncDtTm>2024-04-23T15:44:45</AccptncDtTm><IntrBkSttlmDt>2024-04-23</IntrBkSttlmDt></RltdDts></TxDtls><TxDtls><Refs><TxId>101356</TxId></Refs><Amt Ccy="EUR">1490</Amt><CdtDbtInd>DBIT</CdtDbtInd><RltdAgts><DbtrAgt><FinInstnId><BICFI>DEUTBEB4NDX</BICFI></FinInstnId></DbtrAgt><CdtrAgt><FinInstnId><BICFI>BKAUGBG9PHG</BICFI></FinInstnId></CdtrAgt></RltdAgts><RltdDts><AccptncDtTm>2024-04-23T15:38:02</AccptncDtTm><IntrBkSttlmDt>2024-04-23</IntrBkSttlmDt></RltdDts></TxDtls><TxDtls><Refs><TxId>707397</TxId></Refs><Amt Ccy="EUR">5</Amt><CdtDbtInd>DBIT</CdtDbtInd><RltdAgts><DbtrAgt><FinInstnId><BICFI>DEUTBEB4NDX</BICFI></FinInstnId></DbtrAgt><CdtrAgt><FinInstnId><BICFI>HBUKFRJ3JDC</BICFI></FinInstnId></CdtrAgt></RltdAgts><RltdDts><AccptncDtTm>2024-04-23T15:34:13</AccptncDtTm><IntrBkSttlmDt>2024-04-23</IntrBkSttlmDt></RltdDts></TxDtls><TxDtls><Refs><TxId>778796</TxId></Refs><Amt Ccy="EUR">40</Amt><CdtDbtInd>CRDT</CdtDbtInd><RltdAgts><DbtrAgt><FinInstnId><BICFI>HBUKFRR0SBV</BICFI></FinInstnId></DbtrAgt><CdtrAgt><FinInstnId><BICFI>SWEDBEM1</BICFI></FinInstnId></CdtrAgt></RltdAgts><RltdDts><AccptncDtTm>2024-04-23T15:19:48</AccptncDtTm><IntrBkSttlmDt>2024-04-23</IntrBkSttlmDt></RltdDts></TxDtls><TxDtls><Refs><TxId>546147</TxId></Refs><Amt Ccy="EUR">8</Amt><CdtDbtInd>DBIT</CdtDbtInd><RltdAgts><DbtrAgt><FinInstnId><BICFI>DEUTBEB4NDX</BICFI></FinInstnId></DbtrAgt><CdtrAgt><FinInstnId><BICFI>HBUKFRJ3JDC</BICFI></FinInstnId></CdtrAgt></RltdAgts><RltdDts><AccptncDtTm>2024-04-23T15:15:24</AccptncDtTm><IntrBkSttlmDt>2024-04-23</IntrBkSttlmDt></RltdDts></TxDtls><TxDtls><Refs><TxId>682979</TxId></Refs><Amt Ccy="EUR">10</Amt><CdtDbtInd>DBIT</CdtDbtInd><RltdAgts><DbtrAgt><FinInstnId><BICFI>DEUTBEB4NDX</BICFI></FinInstnId></DbtrAgt><CdtrAgt><FinInstnId><BICFI>SWEDFRF9QVG</BICFI></FinInstnId></CdtrAgt></RltdAgts><RltdDts><AccptncDtTm>2024-04-23T15:12:20</AccptncDtTm><IntrBkSttlmDt>2024-04-23</IntrBkSttlmDt></RltdDts></TxDtls><TxDtls><Refs><TxId>534990</TxId></Refs><Amt Ccy="EUR">10</Amt><CdtDbtInd>DBIT</CdtDbtInd><RltdAgts><DbtrAgt><FinInstnId><BICFI>DEUTBEB4NDX</BICFI></FinInstnId></DbtrAgt><CdtrAgt><FinInstnId><BICFI>SWEDFRF9QVG</BICFI></FinInstnId></CdtrAgt></RltdAgts><RltdDts><AccptncDtTm>2024-04-23T15:08:24</AccptncDtTm><IntrBkSttlmDt>2024-04-23</IntrBkSttlmDt></RltdDts></TxDtls><TxDtls><Refs><TxId>715087</TxId></Refs><Amt Ccy="EUR">77</Amt><CdtDbtInd>CRDT</CdtDbtInd><RltdAgts><DbtrAgt><FinInstnId><BICFI>GEBAFRG3DEH</BICFI></FinInstnId></DbtrAgt><CdtrAgt><FinInstnId><BICFI>DEUTBEB4NDX</BICFI></FinInstnId></CdtrAgt></RltdAgts><RltdDts><AccptncDtTm>2024-04-23T14:55:22</AccptncDtTm><IntrBkSttlmDt>2024-04-23</IntrBkSttlmDt></RltdDts></TxDtls><TxDtls><Refs><TxId>230060</TxId></Refs><Amt Ccy="EUR">30</Amt><CdtDbtInd>CRDT</CdtDbtInd><RltdAgts><DbtrAgt><FinInstnId><BICFI>GEBAFRG3DEH</BICFI></FinInstnId></DbtrAgt><CdtrAgt><FinInstnId><BICFI>DEUTBEB4NDX</BICFI></FinInstnId></CdtrAgt></RltdAgts><RltdDts><AccptncDtTm>2024-04-23T14:55:16</AccptncDtTm><IntrBkSttlmDt>2024-04-23</IntrBkSttlmDt></RltdDts></TxDtls><TxDtls><Refs><TxId>578764</TxId></Refs><Amt Ccy="EUR">100</Amt><CdtDbtInd>DBIT</CdtDbtInd><RltdAgts><DbtrAgt><FinInstnId><BICFI>DEUTBEB4NDX</BICFI></FinInstnId></DbtrAgt><CdtrAgt><FinInstnId><BICFI>BKAUBEJ1DYS</BICFI></FinInstnId></CdtrAgt></RltdAgts><RltdDts><AccptncDtTm>2024-04-23T14:46:59</AccptncDtTm><IntrBkSttlmDt>2024-04-23</IntrBkSttlmDt></RltdDts></TxDtls><TxDtls><Refs><TxId>894669</TxId></Refs><Amt Ccy="EUR">30</Amt><CdtDbtInd>CRDT</CdtDbtInd><RltdAgts><DbtrAgt><FinInstnId><BICFI>SWEDFRM3RTS</BICFI></FinInstnId></DbtrAgt><CdtrAgt><FinInstnId><BICFI>DEUTBEB4NDX</BICFI></FinInstnId></CdtrAgt></RltdAgts><RltdDts><AccptncDtTm>2024-04-23T14:35:43</AccptncDtTm><IntrBkSttlmDt>2024-04-23</IntrBkSttlmDt></RltdDts></TxDtls><TxDtls><Refs><TxId>813674</TxId></Refs><Amt Ccy="EUR">500</Amt><CdtDbtInd>CRDT</CdtDbtInd><RltdAgts><DbtrAgt><FinInstnId><BICFI>SWEDFRM3RTS</BICFI></FinInstnId></DbtrAgt><CdtrAgt><FinInstnId><BICFI>DEUTBEB4NDX</BICFI></FinInstnId></CdtrAgt></RltdAgts><RltdDts><AccptncDtTm>2024-04-23T14:33:35</AccptncDtTm><IntrBkSttlmDt>2024-04-23</IntrBkSttlmDt></RltdDts></TxDtls><TxDtls><Refs><TxId>174945</TxId></Refs><Amt Ccy="EUR">10</Amt><CdtDbtInd>DBIT</CdtDbtInd><RltdAgts><DbtrAgt><FinInstnId><BICFI>DEUTBEB4NDX</BICFI></FinInstnId></DbtrAgt><CdtrAgt><FinInstnId><BICFI>INGBFRW3IUA</BICFI></FinInstnId></CdtrAgt></RltdAgts><RltdDts><AccptncDtTm>2024-04-23T14:26:49</AccptncDtTm><IntrBkSttlmDt>2024-04-23</IntrBkSttlmDt></RltdDts></TxDtls><TxDtls><Refs><TxId>763705</TxId></Refs><Amt Ccy="EUR">630</Amt><CdtDbtInd>CRDT</CdtDbtInd><RltdAgts><DbtrAgt><FinInstnId><BICFI>SWEDBEN7RMQ</BICFI></FinInstnId></DbtrAgt><CdtrAgt><FinInstnId><BICFI>DEUTBEB4NDX</BICFI></FinInstnId></CdtrAgt></RltdAgts><RltdDts><AccptncDtTm>2024-04-23T14:26:35</AccptncDtTm><IntrBkSttlmDt>2024-04-23</IntrBkSttlmDt></RltdDts></TxDtls><TxDtls><Refs><TxId>715844</TxId></Refs><Amt Ccy="EUR">500</Amt><CdtDbtInd>CRDT</CdtDbtInd><RltdAgts><DbtrAgt><FinInstnId><BICFI>GEBAFRG3DEH</BICFI></FinInstnId></DbtrAgt><CdtrAgt><FinInstnId><BICFI>DEUTBEB4NDX</BICFI></FinInstnId></CdtrAgt></RltdAgts><RltdDts><AccptncDtTm>2024-04-23T14:25:36</AccptncDtTm><IntrBkSttlmDt>2024-04-23</IntrBkSttlmDt></RltdDts></TxDtls><TxDtls><Refs><TxId>984929</TxId></Refs><Amt Ccy="EUR">140</Amt><CdtDbtInd>CRDT</CdtDbtInd><RltdAgts><DbtrAgt><FinInstnId><BICFI>HBUKFRJ3JDC</BICFI></FinInstnId></DbtrAgt><CdtrAgt><FinInstnId><BICFI>DEUTBEB4NDX</BICFI></FinInstnId></CdtrAgt></RltdAgts><RltdDts><AccptncDtTm>2024-04-23T14:20:34</AccptncDtTm><IntrBkSttlmDt>2024-04-23</IntrBkSttlmDt></RltdDts></TxDtls><TxDtls><Refs><TxId>418996</TxId></Refs><Amt Ccy="EUR">10</Amt><CdtDbtInd>CRDT</CdtDbtInd><RltdAgts><DbtrAgt><FinInstnId><BICFI>HBUKFRO7AER</BICFI></FinInstnId></DbtrAgt><CdtrAgt><FinInstnId><BICFI>DEUTBEB4NDX</BICFI></FinInstnId></CdtrAgt></RltdAgts><RltdDts><AccptncDtTm>2024-04-23T14:11:02</AccptncDtTm><IntrBkSttlmDt>2024-04-23</IntrBkSttlmDt></RltdDts></TxDtls><TxDtls><Refs><TxId>388228</TxId></Refs><Amt Ccy="EUR">160</Amt><CdtDbtInd>CRDT</CdtDbtInd><RltdAgts><DbtrAgt><FinInstnId><BICFI>SWEDBEN7RMQ</BICFI></FinInstnId></DbtrAgt><CdtrAgt><FinInstnId><BICFI>DEUTBEB4NDX</BICFI></FinInstnId></CdtrAgt></RltdAgts><RltdDts><AccptncDtTm>2024-04-23T13:56:11</AccptncDtTm><IntrBkSttlmDt>2024-04-23</IntrBkSttlmDt></RltdDts></TxDtls><TxDtls><Refs><TxId>205501</TxId></Refs><Amt Ccy="EUR">10.5</Amt><CdtDbtInd>CRDT</CdtDbtInd><RltdAgts><DbtrAgt><FinInstnId><BICFI>HBUKFRO7AER</BICFI></FinInstnId></DbtrAgt><CdtrAgt><FinInstnId><BICFI>DEUTBEB4NDX</BICFI></FinInstnId></CdtrAgt></RltdAgts><RltdDts><AccptncDtTm>2024-04-23T13:38:02</AccptncDtTm><IntrBkSttlmDt>2024-04-23</IntrBkSttlmDt></RltdDts></TxDtls><TxDtls><Refs><TxId>735850</TxId></Refs><Amt Ccy="EUR">500</Amt><CdtDbtInd>CRDT</CdtDbtInd><RltdAgts><DbtrAgt><FinInstnId><BICFI>HBUKFRO7AER</BICFI></FinInstnId></DbtrAgt><CdtrAgt><FinInstnId><BICFI>DEUTBEB4NDX</BICFI></FinInstnId></CdtrAgt></RltdAgts><RltdDts><AccptncDtTm>2024-04-23T13:11:11</AccptncDtTm><IntrBkSttlmDt>2024-04-23</IntrBkSttlmDt></RltdDts></TxDtls><TxDtls><Refs><TxId>142253</TxId></Refs><Amt Ccy="EUR">60</Amt><CdtDbtInd>CRDT</CdtDbtInd><RltdAgts><DbtrAgt><FinInstnId><BICFI>SWEDFRF9QVG</BICFI></FinInstnId></DbtrAgt><CdtrAgt><FinInstnId><BICFI>DEUTBEB4NDX</BICFI></FinInstnId></CdtrAgt></RltdAgts><RltdDts><AccptncDtTm>2024-04-23T13:09:10</AccptncDtTm><IntrBkSttlmDt>2024-04-23</IntrBkSttlmDt></RltdDts></TxDtls><TxDtls><Refs><TxId>160504</TxId></Refs><Amt Ccy="EUR">1500</Amt><CdtDbtInd>CRDT</CdtDbtInd><RltdAgts><DbtrAgt><FinInstnId><BICFI>GEBAITO7JJZ</BICFI></FinInstnId></DbtrAgt><CdtrAgt><FinInstnId><BICFI>DEUTBEB4NDX</BICFI></FinInstnId></CdtrAgt></RltdAgts><RltdDts><AccptncDtTm>2024-04-23T12:53:29</AccptncDtTm><IntrBkSttlmDt>2024-04-23</IntrBkSttlmDt></RltdDts></TxDtls><TxDtls><Refs><TxId>829496</TxId></Refs><Amt Ccy="EUR">90</Amt><CdtDbtInd>DBIT</CdtDbtInd><RltdAgts><DbtrAgt><FinInstnId><BICFI>DEUTBEB4NDX</BICFI></FinInstnId></DbtrAgt><CdtrAgt><FinInstnId><BICFI>FINALTJ2RVE</BICFI></FinInstnId></CdtrAgt></RltdAgts><RltdDts><AccptncDtTm>2024-04-23T12:44:33</AccptncDtTm><IntrBkSttlmDt>2024-04-23</IntrBkSttlmDt></RltdDts></TxDtls><TxDtls><Refs><TxId>289030</TxId></Refs><Amt Ccy="EUR">1060</Amt><CdtDbtInd>DBIT</CdtDbtInd><RltdAgts><DbtrAgt><FinInstnId><BICFI>DEUTBEB4NDX</BICFI></FinInstnId></DbtrAgt><CdtrAgt><FinInstnId><BICFI>FINALTJ2RVE</BICFI></FinInstnId></CdtrAgt></RltdAgts><RltdDts><AccptncDtTm>2024-04-23T12:43:26</AccptncDtTm><IntrBkSttlmDt>2024-04-23</IntrBkSttlmDt></RltdDts></TxDtls><TxDtls><Refs><TxId>253908</TxId></Refs><Amt Ccy="EUR">70</Amt><CdtDbtInd>DBIT</CdtDbtInd><RltdAgts><DbtrAgt><FinInstnId><BICFI>DEUTBEB4NDX</BICFI></FinInstnId></DbtrAgt><CdtrAgt><FinInstnId><BICFI>GEBAFRG3DEH</BICFI></FinInstnId></CdtrAgt></RltdAgts><RltdDts><AccptncDtTm>2024-04-23T12:37:06</AccptncDtTm><IntrBkSttlmDt>2024-04-23</IntrBkSttlmDt></RltdDts></TxDtls><TxDtls><Refs><TxId>147969</TxId></Refs><Amt Ccy="EUR">492.55</Amt><CdtDbtInd>CRDT</CdtDbtInd><RltdAgts><DbtrAgt><FinInstnId><BICFI>GEBAFRG3DEH</BICFI></FinInstnId></DbtrAgt><CdtrAgt><FinInstnId><BICFI>DEUTBEB4NDX</BICFI></FinInstnId></CdtrAgt></RltdAgts><RltdDts><AccptncDtTm>2024-04-23T12:26:58</AccptncDtTm><IntrBkSttlmDt>2024-04-23</IntrBkSttlmDt></RltdDts></TxDtls><TxDtls><Refs><TxId>161123</TxId></Refs><Amt Ccy="EUR">9950</Amt><CdtDbtInd>DBIT</CdtDbtInd><RltdAgts><DbtrAgt><FinInstnId><BICFI>DEUTBEB4NDX</BICFI></FinInstnId></DbtrAgt><CdtrAgt><FinInstnId><BICFI>BKAUGBG9PHG</BICFI></FinInstnId></CdtrAgt></RltdAgts><RltdDts><AccptncDtTm>2024-04-23T12:18:28</AccptncDtTm><IntrBkSttlmDt>2024-04-23</IntrBkSttlmDt></RltdDts></TxDtls><TxDtls><Refs><TxId>411009</TxId></Refs><Amt Ccy="EUR">2125</Amt><CdtDbtInd>DBIT</CdtDbtInd><RltdAgts><DbtrAgt><FinInstnId><BICFI>DEUTBEB4NDX</BICFI></FinInstnId></DbtrAgt><CdtrAgt><FinInstnId><BICFI>BKAUGBG9PHG</BICFI></FinInstnId></CdtrAgt></RltdAgts><RltdDts><AccptncDtTm>2024-04-23T12:13:21</AccptncDtTm><IntrBkSttlmDt>2024-04-23</IntrBkSttlmDt></RltdDts></TxDtls><TxDtls><Refs><TxId>610232</TxId></Refs><Amt Ccy="EUR">1</Amt><CdtDbtInd>DBIT</CdtDbtInd><RltdAgts><DbtrAgt><FinInstnId><BICFI>DEUTBEB4NDX</BICFI></FinInstnId></DbtrAgt><CdtrAgt><FinInstnId><BICFI>GEBAFRG3DEH</BICFI></FinInstnId></CdtrAgt></RltdAgts><RltdDts><AccptncDtTm>2024-04-23T12:12:23</AccptncDtTm><IntrBkSttlmDt>2024-04-23</IntrBkSttlmDt></RltdDts></TxDtls><TxDtls><Refs><TxId>175218</TxId></Refs><Amt Ccy="EUR">50</Amt><CdtDbtInd>DBIT</CdtDbtInd><RltdAgts><DbtrAgt><FinInstnId><BICFI>DEUTBEB4NDX</BICFI></FinInstnId></DbtrAgt><CdtrAgt><FinInstnId><BICFI>FINALTJ2RVE</BICFI></FinInstnId></CdtrAgt></RltdAgts><RltdDts><AccptncDtTm>2024-04-23T12:11:44</AccptncDtTm><IntrBkSttlmDt>2024-04-23</IntrBkSttlmDt></RltdDts></TxDtls><TxDtls><Refs><TxId>112038</TxId></Refs><Amt Ccy="EUR">55</Amt><CdtDbtInd>DBIT</CdtDbtInd><RltdAgts><DbtrAgt><FinInstnId><BICFI>DEUTBEB4NDX</BICFI></FinInstnId></DbtrAgt><CdtrAgt><FinInstnId><BICFI>GEBAFRG3DEH</BICFI></FinInstnId></CdtrAgt></RltdAgts><RltdDts><AccptncDtTm>2024-04-23T12:11:39</AccptncDtTm><IntrBkSttlmDt>2024-04-23</IntrBkSttlmDt></RltdDts></TxDtls><TxDtls><Refs><TxId>341125</TxId></Refs><Amt Ccy="EUR">2000</Amt><CdtDbtInd>CRDT</CdtDbtInd><RltdAgts><DbtrAgt><FinInstnId><BICFI>FINABEX5AVM</BICFI></FinInstnId></DbtrAgt><CdtrAgt><FinInstnId><BICFI>DEUTBEB4NDX</BICFI></FinInstnId></CdtrAgt></RltdAgts><RltdDts><AccptncDtTm>2024-04-23T11:56:50</AccptncDtTm><IntrBkSttlmDt>2024-04-23</IntrBkSttlmDt></RltdDts></TxDtls><TxDtls><Refs><TxId>950997</TxId></Refs><Amt Ccy="EUR">1</Amt><CdtDbtInd>DBIT</CdtDbtInd><RltdAgts><DbtrAgt><FinInstnId><BICFI>DEUTBEB4NDX</BICFI></FinInstnId></DbtrAgt><CdtrAgt><FinInstnId><BICFI>GEBAFRI5BAY</BICFI></FinInstnId></CdtrAgt></RltdAgts><RltdDts><AccptncDtTm>2024-04-23T11:46:49</AccptncDtTm><IntrBkSttlmDt>2024-04-23</IntrBkSttlmDt></RltdDts></TxDtls><TxDtls><Refs><TxId>474515</TxId></Refs><Amt Ccy="EUR">50</Amt><CdtDbtInd>CRDT</CdtDbtInd><RltdAgts><DbtrAgt><FinInstnId><BICFI>HBUKFRO7AER</BICFI></FinInstnId></DbtrAgt><CdtrAgt><FinInstnId><BICFI>DEUTBEB4NDX</BICFI></FinInstnId></CdtrAgt></RltdAgts><RltdDts><AccptncDtTm>2024-04-23T11:40:21</AccptncDtTm><IntrBkSttlmDt>2024-04-23</IntrBkSttlmDt></RltdDts></TxDtls><TxDtls><Refs><TxId>935544</TxId></Refs><Amt Ccy="EUR">300</Amt><CdtDbtInd>CRDT</CdtDbtInd><RltdAgts><DbtrAgt><FinInstnId><BICFI>HBUKFRO7AER</BICFI></FinInstnId></DbtrAgt><CdtrAgt><FinInstnId><BICFI>DEUTBEB4NDX</BICFI></FinInstnId></CdtrAgt></RltdAgts><RltdDts><AccptncDtTm>2024-04-23T11:37:48</AccptncDtTm><IntrBkSttlmDt>2024-04-23</IntrBkSttlmDt></RltdDts></TxDtls><TxDtls><Refs><TxId>567652</TxId></Refs><Amt Ccy="EUR">5</Amt><CdtDbtInd>DBIT</CdtDbtInd><RltdAgts><DbtrAgt><FinInstnId><BICFI>DEUTBEB4NDX</BICFI></FinInstnId></DbtrAgt><CdtrAgt><FinInstnId><BICFI>KREDFRC8QER</BICFI></FinInstnId></CdtrAgt></RltdAgts><RltdDts><AccptncDtTm>2024-04-23T11:26:12</AccptncDtTm><IntrBkSttlmDt>2024-04-23</IntrBkSttlmDt></RltdDts></TxDtls><TxDtls><Refs><TxId>661625</TxId></Refs><Amt Ccy="EUR">30</Amt><CdtDbtInd>DBIT</CdtDbtInd><RltdAgts><DbtrAgt><FinInstnId><BICFI>DEUTBEB4NDX</BICFI></FinInstnId></DbtrAgt><CdtrAgt><FinInstnId><BICFI>GEBAFRG3DEH</BICFI></FinInstnId></CdtrAgt></RltdAgts><RltdDts><AccptncDtTm>2024-04-23T11:25:06</AccptncDtTm><IntrBkSttlmDt>2024-04-23</IntrBkSttlmDt></RltdDts></TxDtls><TxDtls><Refs><TxId>541317</TxId></Refs><Amt Ccy="EUR">90</Amt><CdtDbtInd>DBIT</CdtDbtInd><RltdAgts><DbtrAgt><FinInstnId><BICFI>DEUTBEB4NDX</BICFI></FinInstnId></DbtrAgt><CdtrAgt><FinInstnId><BICFI>GEBAFRG3DEH</BICFI></FinInstnId></CdtrAgt></RltdAgts><RltdDts><AccptncDtTm>2024-04-23T11:21:57</AccptncDtTm><IntrBkSttlmDt>2024-04-23</IntrBkSttlmDt></RltdDts></TxDtls><TxDtls><Refs><TxId>767242</TxId></Refs><Amt Ccy="EUR">500</Amt><CdtDbtInd>CRDT</CdtDbtInd><RltdAgts><DbtrAgt><FinInstnId><BICFI>HBUKFRO7AER</BICFI></FinInstnId></DbtrAgt><CdtrAgt><FinInstnId><BICFI>DEUTBEB4NDX</BICFI></FinInstnId></CdtrAgt></RltdAgts><RltdDts><AccptncDtTm>2024-04-23T11:09:56</AccptncDtTm><IntrBkSttlmDt>2024-04-23</IntrBkSttlmDt></RltdDts></TxDtls><TxDtls><Refs><TxId>767973</TxId></Refs><Amt Ccy="EUR">40</Amt><CdtDbtInd>DBIT</CdtDbtInd><RltdAgts><DbtrAgt><FinInstnId><BICFI>DEUTBEB4NDX</BICFI></FinInstnId></DbtrAgt><CdtrAgt><FinInstnId><BICFI>GEBAFRS0LVF</BICFI></FinInstnId></CdtrAgt></RltdAgts><RltdDts><AccptncDtTm>2024-04-23T11:02:54</AccptncDtTm><IntrBkSttlmDt>2024-04-23</IntrBkSttlmDt></RltdDts></TxDtls><TxDtls><Refs><TxId>702617</TxId></Refs><Amt Ccy="EUR">500</Amt><CdtDbtInd>CRDT</CdtDbtInd><RltdAgts><DbtrAgt><FinInstnId><BICFI>GEBAFRZ1XAW</BICFI></FinInstnId></DbtrAgt><CdtrAgt><FinInstnId><BICFI>DEUTBEB4NDX</BICFI></FinInstnId></CdtrAgt></RltdAgts><RltdDts><AccptncDtTm>2024-04-23T10:52:15</AccptncDtTm><IntrBkSttlmDt>2024-04-23</IntrBkSttlmDt></RltdDts></TxDtls><TxDtls><Refs><TxId>505941</TxId></Refs><Amt Ccy="EUR">150</Amt><CdtDbtInd>CRDT</CdtDbtInd><RltdAgts><DbtrAgt><FinInstnId><BICFI>BNPAFRM2VFP</BICFI></FinInstnId></DbtrAgt><CdtrAgt><FinInstnId><BICFI>DEUTBEB4NDX</BICFI></FinInstnId></CdtrAgt></RltdAgts><RltdDts><AccptncDtTm>2024-04-23T10:48:23</AccptncDtTm><IntrBkSttlmDt>2024-04-23</IntrBkSttlmDt></RltdDts></TxDtls></NtryDtls></Ntry></Ntfctn></BkToCstmrDbtCdtNtfctn></Document>
